charmeleon/__init__.py
charmeleon/error.py
charmeleon/go/darwin_amd64
charmeleon/go/darwin_amd64.h
charmeleon/go/darwin_arm64
charmeleon/go/darwin_arm64.h
charmeleon/go/linux_amd64
charmeleon/go/linux_amd64.h
charmeleon/go/linux_arm64
charmeleon/go/linux_arm64.h
charmeleon/table/__init__.py
charmeleon/table/alpha.py
charmeleon/table/ascii.py
charmeleon/table/digit.py
charmeleon/table/kana.py
charmeleon/table/punct.py
charmeleon/width.py
charmeleon-0.2.0.dist-info/LICENSE
charmeleon-0.2.0.dist-info/METADATA
charmeleon-0.2.0.dist-info/WHEEL
charmeleon-0.2.0.dist-info/RECORD
