Metadata-Version: 2.1
Name: charmeleon
Version: 0.2.0
Summary: charmeleon is a character conversion library in Python.
Home-page: https://yut-kt.github.io/charmeleon/
License: MIT
Author: yut-kt
Author-email: yut.kt59@gmail.com
Requires-Python: >=3.9,<4.0
Classifier: License :: OSI Approved :: MIT License
Classifier: Programming Language :: Python :: 3
Classifier: Programming Language :: Python :: 3.9
Classifier: Programming Language :: Python :: 3.10
Classifier: Programming Language :: Python :: 3.11
Classifier: Programming Language :: Python :: 3.12
Project-URL: Repository, https://github.com/yut-kt/charmeleon
